<?xml version='1.0'?>
<properties>
      <property>
            <name>folder</name>
            <table>objects</table>
            <group>general</group>
            <type>relpicker</type>
            <reltype>RELTYPE_IMG_FOLDER</reltype>
            <field>meta</field>
            <method>serialize</method>
            <caption>Piltide kataloog</caption>
      </property>
      <property>
            <name>cols</name>
            <table>objects</table>
            <group>general</group>
            <type>textbox</type>
            <size>5</size>
            <field>meta</field>
            <method>serialize</method>
            <default>2</default>
            <caption>Tulpi</caption>
      </property>
      <property>
            <name>rows</name>
            <table>objects</table>
            <group>general</group>
            <type>textbox</type>
            <size>5</size>
            <field>meta</field>
            <method>serialize</method>
            <caption>Ridu</caption>
      </property>
      <property>
            <name>comments</name>
            <table>objects</table>
            <group>general</group>
            <type>checkbox</type>
            <field>flags</field>
            <method>bitmask</method>
            <ch_value>1</ch_value>
            <caption>Pildid kommenteeritavad</caption>
      </property>
      <property>
            <name>style</name>
            <table>objects</table>
            <group>general</group>
            <type>relpicker</type>
            <reltype>RELTYPE_STYLE</reltype>
            <field>meta</field>
            <method>serialize</method>
            <caption>Piltide stiil</caption>
      </property>
      <property>
            <name>zip_file</name>
            <table>objects</table>
            <group>import</group>
            <type>fileupload</type>
            <store>no</store>
            <field>zip_file</field>
            <caption>Uploadi ZIP fail</caption>
      </property>
      <classinfo>
            <syslog_type>ST_MINI_GALLERY</syslog_type>
            <relationmgr>yes</relationmgr>
            <no_status>1</no_status>
      </classinfo>
      <groupinfo>
            <import>
                  <caption>Import</caption>
            </import>
      </groupinfo>
      <reltypes>
            <IMG_FOLDER>
                  <value>1</value>
                  <clid>CL_MENU</clid>
                  <caption>Piltide kataloog</caption>
            </IMG_FOLDER>
            <STYLE>
                  <value>2</value>
                  <clid>CL_CSS</clid>
                  <caption>Stiil</caption>
            </STYLE>
      </reltypes>
</properties>

