<?xml version='1.0'?>
<orb>
	<class name="otto_import" folder="www/automatweb_dev/classes/applications/shop/otto" extends="class_base">
		<action name="do_products_amounts_import" nologin="1">
			<function name="do_products_amounts_import">
				<arguments>
					<required name="id" type="int" />
				</arguments>
			</function>
		</action>

		<action name="get_products_xml">
			<function name="get_products_xml">
				<arguments>
				</arguments>
			</function>
		</action>

		<action name="submit_add_cart" nologin="1">
			<function name="submit_add_cart">
				<arguments>
				</arguments>
			</function>
		</action>

	</class>
</orb>
