<?xml version='1.0'?>
<xml>
<num_0>
      <class>applications/shop/shop_product</class>
      <func>on_add_alias</func>
      <param>CL_SHOP_PRODUCT</param>
</num_0>
<num_1>
      <class>contentmgmt/reminder</class>
      <func>on_rconnect_from</func>
      <param>CL_DOCUMENT</param>
</num_1>
<num_2>
      <class>contentmgmt/timing</class>
      <func>on_tconnect_from</func>
      <param>CL_DOCUMENT</param>
</num_2>
<num_3>
      <class>contentmgmt/timing</class>
      <func>on_tconnect_from</func>
      <param>CL_MENU</param>
</num_3>
<num_4>
      <class>contentmgmt/forum/forum_v2</class>
      <func>on_connect_menu</func>
      <param>CL_FORUM_V2</param>
</num_4>
<num_5>
      <class>core/users/group</class>
      <func>on_add_alias_to_group</func>
      <param>CL_GROUP</param>
</num_5>
<num_6>
      <class>core/users/user</class>
      <func>on_add_alias</func>
      <param>CL_USER</param>
</num_6>
<num_7>
      <class>crm/crm_company</class>
      <func>on_connect_person_to_org</func>
      <param>CL_CRM_PERSON</param>
</num_7>
<num_8>
      <class>crm/crm_company</class>
      <func>on_create_customer</func>
      <param>CL_CRM_CATEGORY</param>
</num_8>
<num_9>
      <class>crm/crm_person</class>
      <func>on_connect_org_to_person</func>
      <param>CL_CRM_COMPANY</param>
</num_9>
<num_10>
      <class>crm/crm_person</class>
      <func>on_connect_section_to_person</func>
      <param>CL_CRM_SECTION</param>
</num_10>
<num_11>
      <class>crm/crm_section</class>
      <func>on_connect_person_to_section</func>
      <param>CL_CRM_PERSON</param>
</num_11>
</xml>
